MANIFEST.in
README.md
dj_mongo_database_url.py
setup.py
dj_mongo_database_url.egg-info/PKG-INFO
dj_mongo_database_url.egg-info/SOURCES.txt
dj_mongo_database_url.egg-info/dependency_links.txt
dj_mongo_database_url.egg-info/not-zip-safe
dj_mongo_database_url.egg-info/top_level.txt