Metadata-Version: 1.0
Name: dj-mongo-database-url
Version: 0.1.1
Summary: Use MongoDB Database URLs in your Django Application.
Home-page: https://github.com/RyanBalfanz/django-mongo-database-url
Author: Ryan Balfanz
Author-email: ryan@ryanbalfanz.net
License: UNKNOWN
Platform: any
Classifier: Environment :: Web Environment
Classifier: Intended Audience :: Developers
Classifier: Operating System :: OS Independent
Classifier: Programming Language :: Python
Classifier: Topic :: Internet :: WWW/HTTP :: Dynamic Content
Classifier: Topic :: Software Development :: Libraries :: Python Modules
